pySIMsalabim/__init__.py
pySIMsalabim/aux_funcs/PathChecksWin.py
pySIMsalabim/aux_funcs/SCLC_funcs.py
pySIMsalabim/aux_funcs/__init__.py
pySIMsalabim/aux_funcs/addons.py
pySIMsalabim/experiments/CV.py
pySIMsalabim/experiments/EQE.py
pySIMsalabim/experiments/JV_steady_state.py
pySIMsalabim/experiments/JV_sweep.py
pySIMsalabim/experiments/__init__.py
pySIMsalabim/experiments/hysteresis.py
pySIMsalabim/experiments/impedance.py
pySIMsalabim/experiments/imps.py
pySIMsalabim/install/__init__.py
pySIMsalabim/install/compile_simsalabim.py
pySIMsalabim/install/get_SIMsalabim.py
pySIMsalabim/install/get_gnu_parallel.py
pySIMsalabim/plots/__init__.py
pySIMsalabim/plots/band_diagram.py
pySIMsalabim/plots/plot_def.py
pySIMsalabim/plots/plot_functions.py
pySIMsalabim/tests/__init__.py
pySIMsalabim/tests/test_CV.py
pySIMsalabim/tests/test_EQE.py
pySIMsalabim/tests/test_IMPS.py
pySIMsalabim/tests/test_JV.py
pySIMsalabim/tests/test_JV_sweep.py
pySIMsalabim/tests/test_hyst.py
pySIMsalabim/tests/test_impedance.py
pySIMsalabim/utils/__init__.py
pySIMsalabim/utils/clean_up.py
pySIMsalabim/utils/device_parameters.py
pySIMsalabim/utils/general.py
pySIMsalabim/utils/parallel_sim.py
pySIMsalabim/utils/utils.py
pysimsalabim-1.3.dist-info/licenses/LICENSE
pysimsalabim-1.3.dist-info/METADATA
pysimsalabim-1.3.dist-info/WHEEL
pysimsalabim-1.3.dist-info/top_level.txt
pysimsalabim-1.3.dist-info/RECORD
