Metadata-Version: 2.4
Name: pySIMsalabim
Version: 1.3
Home-page: https://github.com/kostergroup/pySIMsalabim
Download-URL: https://github.com/kostergroup/pySIMsalabim/v1.03.tar.gz
Author: Vincent M. Le Corre, Sander Heester, L. Jan Anton Koster
Author-email: 
License: GPLv3
Keywords: Drift-diffusion,semiconductor,solar cells
Classifier: Programming Language :: Python :: 3
Classifier: Intended Audience :: Science/Research
Classifier: Operating System :: OS Independent
Classifier: License :: OSI Approved :: GNU General Public License v3 (GPLv3)
Requires-Python: >=3.12
License-File: LICENSE
Requires-Dist: numpy<=2.0,>=1.2
Requires-Dist: pandas>=1.4
Requires-Dist: matplotlib>=3.5
Requires-Dist: jupyterlab>=3.4
Requires-Dist: seaborn>=0.11
Requires-Dist: scipy>=1.0
Requires-Dist: gitpython>=3.1
Requires-Dist: openpyxl>=3.0
Provides-Extra: dev
Requires-Dist: pytest; extra == "dev"
Requires-Dist: twine; extra == "dev"
Dynamic: author
Dynamic: classifier
Dynamic: description
Dynamic: description-content-type
Dynamic: download-url
Dynamic: home-page
Dynamic: keywords
Dynamic: license
Dynamic: license-file
Dynamic: provides-extra
Dynamic: requires-dist
Dynamic: requires-python
